README.rst
setup.py
mnctools/__init__.py
mnctools/mnctools.py
mnctools.egg-info/PKG-INFO
mnctools.egg-info/SOURCES.txt
mnctools.egg-info/dependency_links.txt
mnctools.egg-info/requires.txt
mnctools.egg-info/top_level.txt